qnet_qsd/__init__.py
qnet_qsd-0.1.0.dist-info/DESCRIPTION.rst
qnet_qsd-0.1.0.dist-info/METADATA
qnet_qsd-0.1.0.dist-info/RECORD
qnet_qsd-0.1.0.dist-info/WHEEL
qnet_qsd-0.1.0.dist-info/dependency_links.txt
qnet_qsd-0.1.0.dist-info/metadata.json
qnet_qsd-0.1.0.dist-info/top_level.txt
